setup.py
need/__init__.py
need/test.py
need.egg-info/PKG-INFO
need.egg-info/SOURCES.txt
need.egg-info/dependency_links.txt
need.egg-info/not-zip-safe
need.egg-info/top_level.txt