Metadata-Version: 1.0
Name: need
Version: 0.1
Summary: NEED TO LEARN
Home-page: http://github.com/jasmine/need
Author: jasneed
Author-email: jasneed@example.com
License: MIT
Platform: UNKNOWN
